dash_react_json_schema_form/DashReactJsonSchemaForm.py
dash_react_json_schema_form/__init__.py
dash_react_json_schema_form/_imports_.py
dash_react_json_schema_form/dash_react_json_schema_form.min.js
dash_react_json_schema_form/dash_react_json_schema_form.min.js.map
dash_react_json_schema_form/metadata.json
dash_react_json_schema_form/package-info.json
dash_react_json_schema_form-0.1.15.dist-info/LICENSE
dash_react_json_schema_form-0.1.15.dist-info/METADATA
dash_react_json_schema_form-0.1.15.dist-info/WHEEL
dash_react_json_schema_form-0.1.15.dist-info/top_level.txt
dash_react_json_schema_form-0.1.15.dist-info/RECORD
