Metadata-Version: 2.1
Name: dash-react-json-schema-form
Version: 0.1.15
Summary: Use React JSON Schema Form w with Dash
Author: Jillian Rowe <jillian@dabbleofdevops.com>
License: Apache-2.0
Platform: UNKNOWN
Classifier: Framework :: Dash
License-File: LICENSE
